{
  "project_info": {
    "project_number": "582678606212",
    "firebase_url": "https://umefirebaseproject-a95c9.firebaseio.com",
    "project_id": "umefirebaseproject-a95c9",
    "storage_bucket": "umefirebaseproject-a95c9.appspot.com"
  },
  "client": [
    {
      "client_info": {
        "mobilesdk_app_id": "1:582678606212:android:6b741d8f2f2c177c",
        "android_client_info": {
          "package_name": "com.umetechnologypvt.ume"
        }
      },
      "oauth_client": [
        {
          "client_id": "582678606212-a15brfbe1osbhq2tcqkp55djih58kdsg.apps.googleusercontent.com",
          "client_type": 1,
          "android_info": {
            "package_name": "com.umetechnologypvt.ume",
            "certificate_hash": "fa7734f56677f3ea319837d95cad6564d25b63ef"
          }
        }
      ],
      "api_key": [
        {
          "current_key": "AIzaSyDVbITV-wIpCcdW6k1r0X2y0CRci55xFao"
        }
      ],
      "services": {
        "appinvite_service": {
          "other_platform_oauth_client": []
        }
      },
      "admob_app_id": "ca-app-pub-1736294279767272~1416977197"
    }
  ],
  "configuration_version": "1"
}