{
  "Countries": [
    {
      "countryName": "Afghanistan",
      "picUrl": "https://firebasestorage.googleapis.com/v0/b/toolsbazzar.appspot.com/o/Photos%2F3fe594585fec9846?alt=media&token=e6c885be-9743-4e4d-86cf-0aabea00f39f"
    },
    {
      "countryName": "Germany",
      "picUrl": "https://firebasestorage.googleapis.com/v0/b/toolsbazzar.appspot.com/o/Photos%2F3fef0a8f63cfbc62?alt=media&token=8672d12f-9956-4084-9a40-8d85c0b8f9b1"
    },
    {
      "countryName": "United Arab Emirates",
      "picUrl": "https://firebasestorage.googleapis.com/v0/b/toolsbazzar.appspot.com/o/Photos%2F3fa2c8e965a47a10?alt=media&token=384ccf70-403f-4b75-864e-70ec03c9f317"
    },
    {
      "countryName": "United Kingdom",
      "picUrl": "https://firebasestorage.googleapis.com/v0/b/toolsbazzar.appspot.com/o/Photos%2F3feb8249edff9a93?alt=media&token=183241a8-9b6a-405d-abad-086c979a3c7e"
    },
    {
      "countryName": "United States",
      "picUrl": "https://firebasestorage.googleapis.com/v0/b/toolsbazzar.appspot.com/o/Photos%2F3fe4e6d3495d1111?alt=media&token=954cb185-41db-4bd5-926d-b3a7f930e7de"
    },
    {
      "countryName": "Sweden",
      "picUrl": "https://firebasestorage.googleapis.com/v0/b/toolsbazzar.appspot.com/o/Photos%2F3fe27c32f5d6d197?alt=media&token=76443e7f-c75a-4be0-b3fd-0815ec3d8390"
    },
    {
      "countryName": "Spain",
      "picUrl": "https://firebasestorage.googleapis.com/v0/b/toolsbazzar.appspot.com/o/Photos%2F3faa628af3bb06d0?alt=media&token=012f4f9a-344d-4ea0-8a5f-f0ab81f709a0"
    },
    {
      "countryName": "Argentina",
      "picUrl": "https://firebasestorage.googleapis.com/v0/b/toolsbazzar.appspot.com/o/Photos%2F3fc0894b0a89a16c?alt=media&token=d8004045-893a-458c-bc28-3bb1921b3640"
    },
    {
      "countryName": "Belarus",
      "picUrl": "https://firebasestorage.googleapis.com/v0/b/toolsbazzar.appspot.com/o/Photos%2F3fd60d98d3a35f20?alt=media&token=e2e76ec9-1e94-4ea0-b353-d25b186eb1b2"
    },
    {
      "countryName": "Belgium",
      "picUrl": "https://firebasestorage.googleapis.com/v0/b/toolsbazzar.appspot.com/o/Photos%2F3fb4631fb88924a8?alt=media&token=8e15eb87-8508-4ef8-bef1-cff648512c0b"
    },
    {
      "countryName": "Finland",
      "picUrl": "https://firebasestorage.googleapis.com/v0/b/toolsbazzar.appspot.com/o/Photos%2F3fc431800e495f08?alt=media&token=60b7b024-4555-467b-83a4-21455f1b3c71"
    },
    {
      "countryName": "France",
      "picUrl": "https://firebasestorage.googleapis.com/v0/b/toolsbazzar.appspot.com/o/Photos%2F3fcdd510f0a7804c?alt=media&token=2a13e738-17dd-42be-a58d-4c6ea3b30726"
    },
    {
      "countryName": "Hong Kong",
      "picUrl": "https://firebasestorage.googleapis.com/v0/b/toolsbazzar.appspot.com/o/Photos%2F3fe5ee8f6de033c9?alt=media&token=fbe74c45-6bf2-4cb0-982d-d0af2035344d"
    },
    {
      "countryName": "Hungary",
      "picUrl": "https://firebasestorage.googleapis.com/v0/b/toolsbazzar.appspot.com/o/Photos%2F3fe30e63f3df3df2?alt=media&token=2c6906de-16aa-4c2e-8702-5047c7735cfa"
    },
    {
      "countryName": "Iceland",
      "picUrl": "https://firebasestorage.googleapis.com/v0/b/toolsbazzar.appspot.com/o/Photos%2F3fcf93975e77a57c?alt=media&token=cdbe8ec4-720a-441c-84d4-dfbf32c1f34b"
    },
    {
      "countryName": "India",
      "picUrl": "https://firebasestorage.googleapis.com/v0/b/toolsbazzar.appspot.com/o/Photos%2F3fe3ce2e433414a6?alt=media&token=24fb02f3-c2d5-4b7f-b410-62cb24acfd59"
    },
    {
      "countryName": "Indonesia",
      "picUrl": "https://firebasestorage.googleapis.com/v0/b/toolsbazzar.appspot.com/o/Photos%2F3fdd5138c6ed08ae?alt=media&token=57362351-2c24-4dd2-ba2d-fe26242d1831"
    },
    {
      "countryName": "Iran",
      "picUrl": "https://firebasestorage.googleapis.com/v0/b/toolsbazzar.appspot.com/o/Photos%2F3fdc9f3e4d9c199a?alt=media&token=8327f4c2-1809-4478-85eb-35bd1ff64b56"
    },
    {
      "countryName": "Iraq",
      "picUrl": "https://firebasestorage.googleapis.com/v0/b/toolsbazzar.appspot.com/o/Photos%2F3feb07b5e488f039?alt=media&token=a3843e94-d042-4d57-8be0-3bdf56fc6e45"
    },
    {
      "countryName": "Ireland",
      "picUrl": "https://firebasestorage.googleapis.com/v0/b/toolsbazzar.appspot.com/o/Photos%2F3fda5e5d888083f6?alt=media&token=88f92bdf-2733-4a8d-9143-f43428bd87e1"
    },
    {
      "countryName": "Israel",
      "picUrl": "https://firebasestorage.googleapis.com/v0/b/toolsbazzar.appspot.com/o/Photos%2F3fbe803877f1c1a8?alt=media&token=50dbecba-3d3f-447c-aca4-f8508a21d51b"
    },
    {
      "countryName": "Italy",
      "picUrl": "https://firebasestorage.googleapis.com/v0/b/toolsbazzar.appspot.com/o/Photos%2F3fc4d843936ef9b8?alt=media&token=552f7fdf-ddea-4ba1-a8ce-ebe7debe8936"
    },
    {
      "countryName": "Jamaica",
      "picUrl": "https://firebasestorage.googleapis.com/v0/b/toolsbazzar.appspot.com/o/Photos%2F3fe87313dbea506e?alt=media&token=2bf09d10-fc77-4235-ba1d-bc704d6f40eb"
    },
    {
      "countryName": "Japan",
      "picUrl": "https://firebasestorage.googleapis.com/v0/b/toolsbazzar.appspot.com/o/Photos%2F3fe8b067b9f56ea9?alt=media&token=ced30443-2ac6-463b-ac3e-6c6a5eee46ce"
    },
    {
      "countryName": "Jordan",
      "picUrl": "https://firebasestorage.googleapis.com/v0/b/toolsbazzar.appspot.com/o/Photos%2F3fdfc39af8499320?alt=media&token=db356f28-3154-4d38-b0a1-a13900eb9a73"
    },
    {
      "countryName": "Korea South",
      "picUrl": "https://firebasestorage.googleapis.com/v0/b/toolsbazzar.appspot.com/o/Photos%2F3fe3bdd458930e0e?alt=media&token=e7baa3bc-4ee2-4dec-9995-dd5e31a8942d"
    },
    {
      "countryName": "Kuwait",
      "picUrl": "https://firebasestorage.googleapis.com/v0/b/toolsbazzar.appspot.com/o/Photos%2F3fc1b4117ee87ed0?alt=media&token=00dd0138-8af1-4705-aa90-2a2c9f998058"
    },
    {
      "countryName": "Kyrgyzstan",
      "picUrl": "https://firebasestorage.googleapis.com/v0/b/toolsbazzar.appspot.com/o/Photos%2F3fc33548ea623334?alt=media&token=48260605-b5c7-46a3-9130-8146707e773e"
    },
    {
      "countryName": "Lebanon",
      "picUrl": "https://firebasestorage.googleapis.com/v0/b/toolsbazzar.appspot.com/o/Photos%2F3fdc2b689517a584?alt=media&token=ba754b37-9ccf-4955-a2d1-28e1bcca1200"
    },
    {
      "countryName": "Macau",
      "picUrl": "https://firebasestorage.googleapis.com/v0/b/toolsbazzar.appspot.com/o/Photos%2F3fe7134692283aa1?alt=media&token=ef5d8a66-b16c-403d-8a84-a8d436d59ba9"
    },
    {
      "countryName": "Macedonia",
      "picUrl": "https://firebasestorage.googleapis.com/v0/b/toolsbazzar.appspot.com/o/Photos%2F3fc52a8edf10b240?alt=media&token=675825e4-ce16-40a8-88bb-d12da2f758a8"
    },
    {
      "countryName": "Madagascar",
      "picUrl": "https://firebasestorage.googleapis.com/v0/b/toolsbazzar.appspot.com/o/Photos%2F3fe8d411afbd26ce?alt=media&token=57cccf8d-b042-460f-a677-48e237a027d8"
    },
    {
      "countryName": "Malaysia",
      "picUrl": "https://firebasestorage.googleapis.com/v0/b/toolsbazzar.appspot.com/o/Photos%2F3fedb2f1f81b9415?alt=media&token=e5c70d49-c3db-483e-97c2-cf2afb5bee21"
    },
    {
      "countryName": "Mauritius",
      "picUrl": "https://firebasestorage.googleapis.com/v0/b/toolsbazzar.appspot.com/o/Photos%2F3fc9e724352fa688?alt=media&token=2cd9cefe-23d6-4a3c-ac90-6cfab90675dd"
    },
    {
      "countryName": "Mexico",
      "picUrl": "https://firebasestorage.googleapis.com/v0/b/toolsbazzar.appspot.com/o/Photos%2F3fe51d798e2c5739?alt=media&token=64f6de3d-e7e9-44ca-9dde-2b1e7d52e15a"
    },
    {
      "countryName": "Nigeria",
      "picUrl": "https://firebasestorage.googleapis.com/v0/b/toolsbazzar.appspot.com/o/Photos%2F3fe3c251ab92e949?alt=media&token=5d00c7c5-dd86-474d-8c67-613a086ad965"
    },
    {
      "countryName": "Norway",
      "picUrl": "https://firebasestorage.googleapis.com/v0/b/toolsbazzar.appspot.com/o/Photos%2F3fd05b802771e816?alt=media&token=271d9c0c-3cb0-4adb-b8fe-b3a49bf5aae3"
    },
    {
      "countryName": "Oman",
      "picUrl": "https://firebasestorage.googleapis.com/v0/b/toolsbazzar.appspot.com/o/Photos%2F3fee0f18ec129b64?alt=media&token=1e5f99ac-d580-453f-8371-fa9036a051e5"
    },
    {
      "countryName": "Pakistan",
      "picUrl": "https://firebasestorage.googleapis.com/v0/b/toolsbazzar.appspot.com/o/Photos%2F3fc6439591e678c8?alt=media&token=1a08a6ab-6e5b-4262-ae68-f5aa4caf6229"
    },
    {
      "countryName": "Palestine",
      "picUrl": "https://firebasestorage.googleapis.com/v0/b/toolsbazzar.appspot.com/o/Photos%2F3fd1dd8a10a5b63a?alt=media&token=0d384d17-bcc4-4c76-8b0e-662c26c40b76"
    },
    {
      "countryName": "Panama",
      "picUrl": "https://firebasestorage.googleapis.com/v0/b/toolsbazzar.appspot.com/o/Photos%2F3fe2bb1b9d5e3621?alt=media&token=854fec5c-8930-4e5d-a870-b85e6883d5c4"
    },
    {
      "countryName": "Paraguay",
      "picUrl": "https://firebasestorage.googleapis.com/v0/b/toolsbazzar.appspot.com/o/Photos%2F3fe9c8c174d72332?alt=media&token=64a384a6-a03d-4b4c-93f7-c77738b40269"
    },
    {
      "countryName": "Peru",
      "picUrl": "https://firebasestorage.googleapis.com/v0/b/toolsbazzar.appspot.com/o/Photos%2F3feaad2b6330260d?alt=media&token=298efbe7-acc6-40d8-a3c0-5c960cc308ec"
    },
    {
      "countryName": "Philippines",
      "picUrl": "https://firebasestorage.googleapis.com/v0/b/toolsbazzar.appspot.com/o/Photos%2F3fdc56d10a613b88?alt=media&token=c0fd8176-65a1-4e8d-a050-e1e51911e728"
    },
    {
      "countryName": "Poland",
      "picUrl": "https://firebasestorage.googleapis.com/v0/b/toolsbazzar.appspot.com/o/Photos%2F3fefebd1080f8009?alt=media&token=03294859-b29d-4edf-aea0-e46f1e29e7e1"
    },
    {
      "countryName": "Portugal",
      "picUrl": "https://firebasestorage.googleapis.com/v0/b/toolsbazzar.appspot.com/o/Photos%2F3fe71383f8a503d9?alt=media&token=2a2df62e-3c1c-458d-a621-ad263f3bf9b3"
    },
    {
      "countryName": "Qatar",
      "picUrl": "https://firebasestorage.googleapis.com/v0/b/toolsbazzar.appspot.com/o/Photos%2F3fda2a8fb7ee087a?alt=media&token=f18fc5c0-3b9a-42a7-bbf4-174f66ee277b"
    },
    {
      "countryName": "Romania",
      "picUrl": "https://firebasestorage.googleapis.com/v0/b/toolsbazzar.appspot.com/o/Photos%2F3fd5cda79f1b147e?alt=media&token=f31051b1-ef42-4b2e-941a-f5867f05553e"
    },
    {
      "countryName": "Saudi Arabia",
      "picUrl": "https://firebasestorage.googleapis.com/v0/b/toolsbazzar.appspot.com/o/Photos%2F3fe80d5ff8d1a951?alt=media&token=c3765bdc-a64d-4d48-b96a-00ee3634eff6"
    },
    {
      "countryName": "Somalia",
      "picUrl": "https://firebasestorage.googleapis.com/v0/b/toolsbazzar.appspot.com/o/Photos%2F3fefec4c61798acd?alt=media&token=89b77c8b-6e3e-4228-aa15-7e2047dd8172"
    },
    {
      "countryName": "Spain",
      "picUrl": "https://firebasestorage.googleapis.com/v0/b/toolsbazzar.appspot.com/o/Photos%2F3faa628af3bb06d0?alt=media&token=012f4f9a-344d-4ea0-8a5f-f0ab81f709a0"
    },
    {
      "countryName": "Sri Lanka",
      "picUrl": "https://firebasestorage.googleapis.com/v0/b/toolsbazzar.appspot.com/o/Photos%2F3fb1d0ab5d7b43b8?alt=media&token=2e364534-fdc2-4a50-bbe8-5339a70e23a2"
    },
    {
      "countryName": "Sudan",
      "picUrl": "https://firebasestorage.googleapis.com/v0/b/toolsbazzar.appspot.com/o/Photos%2F3fd10d17e8fcf436?alt=media&token=e06585f5-fa44-4836-87f8-c1b8ebacfa7d"
    },
    {
      "countryName": "Swaziland",
      "picUrl": "https://firebasestorage.googleapis.com/v0/b/toolsbazzar.appspot.com/o/Photos%2F3fee3e4f0ef6455a?alt=media&token=39e84c82-36ee-43dd-9005-7587339a1c5f"
    },
    {
      "countryName": "Sweden",
      "picUrl": "https://firebasestorage.googleapis.com/v0/b/toolsbazzar.appspot.com/o/Photos%2F3fe27c32f5d6d197?alt=media&token=76443e7f-c75a-4be0-b3fd-0815ec3d8390"
    },
    {
      "countryName": "Switzerland",
      "picUrl": "https://firebasestorage.googleapis.com/v0/b/toolsbazzar.appspot.com/o/Photos%2F3fd80fdf4a3f1c98?alt=media&token=296f7777-acc3-4cf6-a032-31806774d9fe"
    },
    {
      "countryName": "Syria",
      "picUrl": "https://firebasestorage.googleapis.com/v0/b/toolsbazzar.appspot.com/o/Photos%2F3fec69c96d3597c0?alt=media&token=b114d24b-bf9e-4ed7-974b-065641edd0a4"
    },
    {
      "countryName": "Taiwan",
      "picUrl": "https://firebasestorage.googleapis.com/v0/b/toolsbazzar.appspot.com/o/Photos%2F3fe45aaca31da4d6?alt=media&token=18c0701d-6d0e-45ef-8853-01bac24226c3"
    },
    {
      "countryName": "Turkmenistan",
      "picUrl": "https://firebasestorage.googleapis.com/v0/b/toolsbazzar.appspot.com/o/Photos%2F3fdc6aacee8f7f0c?alt=media&token=9d057f1e-5670-41c6-b1ae-537328d74cd1"
    },
    {
      "countryName": "Ukraine",
      "picUrl": "https://firebasestorage.googleapis.com/v0/b/toolsbazzar.appspot.com/o/Photos%2F3fe47fe9ae377cd0?alt=media&token=27d81023-606e-440a-912b-d82915740c0c"
    },
    {
      "countryName": "Uruguay",
      "picUrl": "https://firebasestorage.googleapis.com/v0/b/toolsbazzar.appspot.com/o/Photos%2F3fdeaa1ba3188d32?alt=media&token=87a42ae1-6aef-4123-b9dd-74912f9caa6f"
    },
    {
      "countryName": "Uzbekistan",
      "picUrl": "https://firebasestorage.googleapis.com/v0/b/toolsbazzar.appspot.com/o/Photos%2F3fbda6dc2f0bb450?alt=media&token=d42a5875-81d0-4da9-b449-9c30e22dbf16"
    },
    {
      "countryName": "Yemen",
      "picUrl": "https://firebasestorage.googleapis.com/v0/b/toolsbazzar.appspot.com/o/Photos%2F3fd35f74ec86d818?alt=media&token=c2a86106-0d5f-4a95-8979-b4447af9cdda"
    },
    {
      "countryName": "Zambia",
      "picUrl": "https://firebasestorage.googleapis.com/v0/b/toolsbazzar.appspot.com/o/Photos%2F3fcaf3f4f833712c?alt=media&token=21984ee4-22ab-4e8c-99a5-d69cae5c1c21"
    }
  ]
}